{
  "project_info": {
    "project_number": "52114916997",
    "project_id": "zidioblogapp",
    "storage_bucket": "zidioblogapp.appspot.com"
  },
  "client": [
    {
      "client_info": {
        "mobilesdk_app_id": "1:52114916997:android:4f98b4b64af75bec0c4bec",
        "android_client_info": {
          "package_name": "com.example.zidioblogapp"
        }
      },
      "oauth_client": [],
      "api_key": [
        {
          "current_key": "AIzaSyDZXMkqAF7kYL0QvzdPsDk_xMvjXvlXkrs"
        }
      ],
      "services": {
        "appinvite_service": {
          "other_platform_oauth_client": []
        }
      }
    }
  ],
  "configuration_version": "1"
}